{"chunk_definitions":[{"row":18,"row_count":1,"visible":true,"expansion_state":0,"options":{"engine":"r","label":"setup","include":false,"dev":"png"},"document_id":"8D22106B","chunk_id":"csetup_chunk","chunk_label":"setup"},{"row":34,"row_count":1,"visible":true,"expansion_state":0,"options":{"engine":"r","label":"unnamed-chunk-17","dev":"png"},"document_id":"8D22106B","chunk_id":"c63bkahxyod3t","chunk_label":"unnamed-chunk-1"},{"row":40,"row_count":1,"visible":true,"expansion_state":0,"options":{"engine":"r","fig.align":"center","label":"unnamed-chunk-18","dev":"png"},"document_id":"8D22106B","chunk_id":"cy63gzilf28yp","chunk_label":"unnamed-chunk-2"},{"row":52,"row_count":1,"visible":true,"expansion_state":0,"options":{"engine":"r","label":"unnamed-chunk-19","dev":"png"},"document_id":"8D22106B","chunk_id":"c8j8h1zhpu4hw","chunk_label":"unnamed-chunk-3"}],"doc_write_time":1741207763,"working_dir":null,"default_chunk_options":{}}